pypipr/ComparePerformance.py
pypipr/LINUX.py
pypipr/PintUreg.py
pypipr/PintUregQuantity.py
pypipr/RunParallel.py
pypipr/WINDOWS.py
pypipr/__init__.py
pypipr/__terminal__.py
pypipr/auto_reload.py
pypipr/batch_calculate.py
pypipr/batchmaker.py
pypipr/calculate.py
pypipr/choices.py
pypipr/chr_to_int.py
pypipr/chunk_array.py
pypipr/create_folder.py
pypipr/datetime_from_string.py
pypipr/datetime_now.py
pypipr/dirname.py
pypipr/dirpath.py
pypipr/django_clear_migrations.py
pypipr/django_runserver.py
pypipr/exit_if_empty.py
pypipr/filter_empty.py
pypipr/get_class_method.py
pypipr/github_init.py
pypipr/github_push.py
pypipr/github_user.py
pypipr/iargv.py
pypipr/idir.py
pypipr/idumps.py
pypipr/idumps_html.py
pypipr/iexec.py
pypipr/iinput.py
pypipr/ijoin.py
pypipr/iloads.py
pypipr/iloads_html.py
pypipr/input_char.py
pypipr/int_to_chr.py
pypipr/iopen.py
pypipr/irange.py
pypipr/ireplace.py
pypipr/is_empty.py
pypipr/is_html.py
pypipr/is_iterable.py
pypipr/is_raw_string.py
pypipr/is_valid_url.py
pypipr/iscandir.py
pypipr/ivars.py
pypipr/log.py
pypipr/pip_freeze_without_version.py
pypipr/pip_update_pypipr.py
pypipr/poetry_publish.py
pypipr/poetry_update_version.py
pypipr/print_colorize.py
pypipr/print_to_last_line.py
pypipr/random_bool.py
pypipr/restart.py
pypipr/set_timeout.py
pypipr/sets_ordered.py
pypipr/sqlite_backup.py
pypipr/sqlite_delete_table.py
pypipr/sqlite_get_all_tables.py
pypipr/sqlite_get_data_table.py
pypipr/text_colorize.py
pypipr-3.0.4.dist-info/entry_points.txt
pypipr-3.0.4.dist-info/WHEEL
pypipr-3.0.4.dist-info/METADATA
pypipr-3.0.4.dist-info/RECORD
