Metadata-Version: 2.4
Name: pypipr
Version: 3.0.4
Summary: The Python Package Index Project
Author-email: ufiapjj <ufiapjj@gmail.com>
Requires-Python: >=3,<4
Requires-Dist: getch ; platform_system == 'Linux'
Requires-Dist: colorama
Requires-Dist: lxml
Requires-Dist: cssselect
Requires-Dist: tzdata
Requires-Dist: requests
Requires-Dist: pyyaml
Requires-Dist: pint
Requires-Dist: django
